unit_grader-1.0.13.dist-info/METADATA
unit_grader-1.0.13.dist-info/WHEEL
unit_grader-1.0.13.dist-info/entry_points.txt
unit_grader-1.0.13.dist-info/licenses/LICENSE
unit_grader/__init__.py
unit_grader/cli.py
unit_grader/commands/__init__.py
unit_grader/commands/conversion_grader.py
unit_grader/config/__init__.py
unit_grader/config/data.py
unit_grader/config/enums.py
unit_grader/utils/__init__.py
unit_grader/utils/common.py
unit_grader-1.0.13.dist-info/RECORD
