Metadata-Version: 2.1
Name: unit-grader
Version: 1.0.13
Summary: Unit Conversion Grader a command-line interface (CLI) program that allows you to convert among units of measurement and grade the users response to determine the result.
Author-Email: simon ouyang <simonouyang@gmail.com>
License: MIT License
Classifier: Development Status :: 5 - Production/Stable
Classifier: Topic :: Utilities
Classifier: Environment :: Console
Classifier: Intended Audience :: Developers
Classifier: Intended Audience :: Education
Classifier: Intended Audience :: End Users/Desktop
Classifier: Programming Language :: Python :: 3
Classifier: Programming Language :: Python :: 3.9
Classifier: Programming Language :: Python :: 3.10
Classifier: Programming Language :: Python :: 3.11
Classifier: Programming Language :: Python :: 3.12
Classifier: Natural Language :: English
Classifier: Operating System :: OS Independent
Classifier: License :: OSI Approved :: MIT License
Project-URL: Documentation, https://unit-grader-api-docs.netlify.app/
Project-URL: Repository, https://github.com/souyang/unit-grader/
Requires-Python: <3.13,>=3.9
Requires-Dist: typer>=0.9.0
Requires-Dist: rich>=13.6.0
Requires-Dist: typing>=3.7.4.3
Requires-Dist: numpy>=1.26.2
